Metadata-Version: 1.0
Name: ahdcmotor
Version: 1.1.2
Summary: DC Motor control module
Home-page: UNKNOWN
Author: Gishnu
Author-email: gishnu@ahdynamics.com
License: MIT
Platform: UNKNOWN
